Metadata-Version: 1.0
Name: Test-MMAI-Api
Version: 0.0.1
Summary: Testing lib deployment to PyPI
Home-page: UNKNOWN
Author: Tomer Efr
Author-email: UNKNOWN
License: MIT
Platform: UNKNOWN
